LICENSE
MANIFEST.in
setup.py
pyactiveresource/__init__.py
pyactiveresource/activeresource.py
pyactiveresource/collection.py
pyactiveresource/connection.py
pyactiveresource/element_containers.py
pyactiveresource/fake_connection.py
pyactiveresource/formats.py
pyactiveresource/util.py
pyactiveresource.egg-info/PKG-INFO
pyactiveresource.egg-info/SOURCES.txt
pyactiveresource.egg-info/dependency_links.txt
pyactiveresource.egg-info/requires.txt
pyactiveresource.egg-info/top_level.txt
pyactiveresource/testing/__init__.py
pyactiveresource/testing/http_fake.py